<?xml version="1.0" encoding="UTF-8"?>
<layout id="null" sceneSize="2048,1300" next="middlefire" previous="opening" eventSheet="fireEventSheet" version="2.2">
  <layer index="0" parallaxX="100" parallaxY="100" layerAlpha="1" layerVisible="false" cacheAsBitmap="false" bgColor="" bgColorAlpha="" layerScaleX="100" layerScaleY="100"/>
  <layer index="1" parallaxX="100" parallaxY="100" layerAlpha="1" layerVisible="false" cacheAsBitmap="false" bgColor="" bgColorAlpha="" layerScaleX="100" layerScaleY="100"/>
  <layer index="2" parallaxX="100" parallaxY="100" layerAlpha="1" layerVisible="false" cacheAsBitmap="false" bgColor="" bgColorAlpha="" layerScaleX="100" layerScaleY="100"/>
  <item UID="3017" plugin="AISprite" name="AISprite3016" cacheAsBitmap="false" parallaxX="100" parallaxY="100" index="0" family="displayobject">
    <item name="name" value="AISprite3016" valueDataType="string"/>
    <item name="uiGuid" value="3017" valueDataType="string"/>
    <item name="global" value="false" valueDataType="boolean"/>
    <item name="visible" value="true" valueDataType="boolean"/>
    <item name="x" value="1031.11815159248" valueDataType="number"/>
    <item name="y" value="591.6884205218964" valueDataType="number"/>
    <item name="anchorX" value="0.5" valueDataType="number"/>
    <item name="anchorY" value="0.5" valueDataType="number"/>
    <item name="width" value="2064.5603547694714" valueDataType="number"/>
    <item name="height" value="1373.6733173530254" valueDataType="number"/>
    <item name="angle" value="359.7049845565877" valueDataType="number"/>
    <item name="alpha" value="1" valueDataType="number"/>
    <item name="url" value="resource%2FuserAsset%2Fimage%2Fblue_grass.png" valueDataType="string"/>
    <item name="enabled" value="false" valueDataType="boolean"/>
    <item name="collision" value="false" valueDataType="boolean"/>
    <item name="collisionData" value="0%2Fn0.00%7C1373.67%2C2064.56%7C1373.67%2C2064.56%7C0.00%2C0.00%7C0.00" sourceValue="0%2Fn0.00%7C1373.67%2C2064.56%7C1373.67%2C2064.56%7C0.00%2C0.00%7C0.00" valueDataType="string"/>
    <item name="layer" value="2" valueDataType="number"/>
  </item>
  <item UID="3020" plugin="AITiledBackground" name="AITiledBackground3019" cacheAsBitmap="false" parallaxX="100" parallaxY="100" index="1" family="displayobject">
    <item name="name" value="AITiledBackground3019" valueDataType="string"/>
    <item name="uiGuid" value="3020" valueDataType="string"/>
    <item name="global" value="false" valueDataType="boolean"/>
    <item name="visible" value="true" valueDataType="boolean"/>
    <item name="x" value="986.5546074706756" valueDataType="number"/>
    <item name="y" value="1019.3259919361136" valueDataType="number"/>
    <item name="anchorX" value="0.5" valueDataType="number"/>
    <item name="anchorY" value="0.5" valueDataType="number"/>
    <item name="width" value="2181.4322560226433" valueDataType="number"/>
    <item name="height" value="127" valueDataType="number"/>
    <item name="angle" value="0" valueDataType="number"/>
    <item name="alpha" value="1" valueDataType="number"/>
    <item name="url" value="resource%2FuserAsset%2Ftt6h80.png" valueDataType="string"/>
    <item name="enabled" value="false" valueDataType="boolean"/>
    <item name="collision" value="true" valueDataType="boolean"/>
    <item name="collisionData" value="0%2Fn0.00%7C127.00%2C2181.43%7C127.00%2C2181.43%7C0.00%2C0.00%7C0.00" sourceValue="0%2Fn0.00%7C127.00%2C2181.43%7C127.00%2C2181.43%7C0.00%2C0.00%7C0.00" valueDataType="string"/>
    <item name="layer" value="2" valueDataType="number"/>
  </item>
  <item UID="3023" plugin="AISprite" name="AISprite3022" cacheAsBitmap="false" parallaxX="100" parallaxY="100" index="2" family="displayobject">
    <item name="name" value="AISprite3022" valueDataType="string"/>
    <item name="uiGuid" value="3023" valueDataType="string"/>
    <item name="global" value="false" valueDataType="boolean"/>
    <item name="visible" value="true" valueDataType="boolean"/>
    <item name="x" value="671.3463980386528" valueDataType="number"/>
    <item name="y" value="623.06" valueDataType="number"/>
    <item name="anchorX" value="0.5" valueDataType="number"/>
    <item name="anchorY" value="0.5" valueDataType="number"/>
    <item name="width" value="128" valueDataType="number"/>
    <item name="height" value="128" valueDataType="number"/>
    <item name="angle" value="0" valueDataType="number"/>
    <item name="alpha" value="1" valueDataType="number"/>
    <item name="url" value="resource%2FuserAsset%2Fimage%2FgrassLeft.png" valueDataType="string"/>
    <item name="enabled" value="false" valueDataType="boolean"/>
    <item name="collision" value="true" valueDataType="boolean"/>
    <item name="collisionData" value="0%2Fn0.00%7C128.00%2C128.00%7C128.00%2C128.00%7C0.00%2C0.00%7C0.00" sourceValue="0%2Fn0.00%7C128.00%2C128.00%7C128.00%2C128.00%7C0.00%2C0.00%7C0.00" valueDataType="string"/>
    <item name="layer" value="2" valueDataType="number"/>
    <item name="behaviors">
      <item type="behavior" behaviorType="SolidBehaivor" name="刚体"/>
    </item>
  </item>
  <item UID="3026" plugin="AISprite" name="AISprite3025" cacheAsBitmap="false" parallaxX="100" parallaxY="100" index="3" family="displayobject">
    <item name="name" value="AISprite3025" valueDataType="string"/>
    <item name="uiGuid" value="3026" valueDataType="string"/>
    <item name="global" value="false" valueDataType="boolean"/>
    <item name="visible" value="true" valueDataType="boolean"/>
    <item name="x" value="1053.2045324156163" valueDataType="number"/>
    <item name="y" value="624.29" valueDataType="number"/>
    <item name="anchorX" value="0.495491420041521" valueDataType="number"/>
    <item name="anchorY" value="0.5002542068101139" valueDataType="number"/>
    <item name="width" value="128" valueDataType="number"/>
    <item name="height" value="128" valueDataType="number"/>
    <item name="angle" value="0" valueDataType="number"/>
    <item name="alpha" value="1" valueDataType="number"/>
    <item name="url" value="resource%2FuserAsset%2Fimage%2FgrassMid.png" valueDataType="string"/>
    <item name="enabled" value="false" valueDataType="boolean"/>
    <item name="collision" value="true" valueDataType="boolean"/>
    <item name="collisionData" value="0%2Fn0.00%7C128.00%2C128.00%7C128.00%2C128.00%7C0.00%2C0.00%7C0.00" sourceValue="0%2Fn0.00%7C128.00%2C128.00%7C128.00%2C128.00%7C0.00%2C0.00%7C0.00" valueDataType="string"/>
    <item name="layer" value="2" valueDataType="number"/>
    <item name="behaviors">
      <item type="behavior" behaviorType="SolidBehaivor" name="刚体"/>
    </item>
  </item>
  <item UID="3029" plugin="AISprite" name="AISprite3028" cacheAsBitmap="false" parallaxX="100" parallaxY="100" index="4" family="displayobject">
    <item name="name" value="AISprite3028" valueDataType="string"/>
    <item name="uiGuid" value="3029" valueDataType="string"/>
    <item name="global" value="false" valueDataType="boolean"/>
    <item name="visible" value="true" valueDataType="boolean"/>
    <item name="x" value="1293.4085896690308" valueDataType="number"/>
    <item name="y" value="614.84" valueDataType="number"/>
    <item name="anchorX" value="0.3917444184735323" valueDataType="number"/>
    <item name="anchorY" value="0.4269401601980789" valueDataType="number"/>
    <item name="width" value="128" valueDataType="number"/>
    <item name="height" value="128" valueDataType="number"/>
    <item name="angle" value="0" valueDataType="number"/>
    <item name="alpha" value="1" valueDataType="number"/>
    <item name="url" value="resource%2FuserAsset%2Fimage%2FgrassRight.png" valueDataType="string"/>
    <item name="enabled" value="false" valueDataType="boolean"/>
    <item name="collision" value="true" valueDataType="boolean"/>
    <item name="collisionData" value="0%2Fn0.00%7C128.00%2C128.00%7C128.00%2C128.00%7C0.00%2C0.00%7C0.00" sourceValue="0%2Fn0.00%7C128.00%2C128.00%7C128.00%2C128.00%7C0.00%2C0.00%7C0.00" valueDataType="string"/>
    <item name="layer" value="2" valueDataType="number"/>
    <item name="behaviors">
      <item type="behavior" behaviorType="SolidBehaivor" name="刚体"/>
    </item>
  </item>
  <item UID="3030" plugin="AISprite" name="AISprite3025" cacheAsBitmap="false" parallaxX="100" parallaxY="100" index="5" family="displayobject">
    <item name="name" value="AISprite3025" valueDataType="string"/>
    <item name="uiGuid" value="3030" valueDataType="string"/>
    <item name="global" value="false" valueDataType="boolean"/>
    <item name="visible" value="true" valueDataType="boolean"/>
    <item name="x" value="1169.749667548236" valueDataType="number"/>
    <item name="y" value="641.29" valueDataType="number"/>
    <item name="anchorX" value="0.4123190521641611" valueDataType="number"/>
    <item name="anchorY" value="0.6348202047502731" valueDataType="number"/>
    <item name="width" value="128" valueDataType="number"/>
    <item name="height" value="128" valueDataType="number"/>
    <item name="angle" value="0" valueDataType="number"/>
    <item name="alpha" value="1" valueDataType="number"/>
    <item name="url" value="resource%2FuserAsset%2Fimage%2FgrassMid.png" valueDataType="string"/>
    <item name="enabled" value="false" valueDataType="boolean"/>
    <item name="collision" value="true" valueDataType="boolean"/>
    <item name="collisionData" value="0%2Fn0.00%7C128.00%2C128.00%7C128.00%2C128.00%7C0.00%2C0.00%7C0.00" sourceValue="0%2Fn0.00%7C128.00%2C128.00%7C128.00%2C128.00%7C0.00%2C0.00%7C0.00" valueDataType="string"/>
    <item name="layer" value="2" valueDataType="number"/>
    <item name="behaviors">
      <item type="behavior" behaviorType="SolidBehaivor" name="刚体"/>
    </item>
  </item>
  <item UID="3031" plugin="AISprite" name="AISprite3025" cacheAsBitmap="false" parallaxX="100" parallaxY="100" index="6" family="displayobject">
    <item name="name" value="AISprite3025" valueDataType="string"/>
    <item name="uiGuid" value="3031" valueDataType="string"/>
    <item name="global" value="false" valueDataType="boolean"/>
    <item name="visible" value="true" valueDataType="boolean"/>
    <item name="x" value="783.6547412949542" valueDataType="number"/>
    <item name="y" value="644.29" valueDataType="number"/>
    <item name="anchorX" value="0.3840291705148893" valueDataType="number"/>
    <item name="anchorY" value="0.6654352820231022" valueDataType="number"/>
    <item name="width" value="128" valueDataType="number"/>
    <item name="height" value="128" valueDataType="number"/>
    <item name="angle" value="0" valueDataType="number"/>
    <item name="alpha" value="1" valueDataType="number"/>
    <item name="url" value="resource%2FuserAsset%2Fimage%2FgrassMid.png" valueDataType="string"/>
    <item name="enabled" value="false" valueDataType="boolean"/>
    <item name="collision" value="true" valueDataType="boolean"/>
    <item name="collisionData" value="0%2Fn0.00%7C128.00%2C128.00%7C128.00%2C128.00%7C0.00%2C0.00%7C0.00" sourceValue="0%2Fn0.00%7C128.00%2C128.00%7C128.00%2C128.00%7C0.00%2C0.00%7C0.00" valueDataType="string"/>
    <item name="layer" value="2" valueDataType="number"/>
    <item name="behaviors">
      <item type="behavior" behaviorType="SolidBehaivor" name="刚体"/>
    </item>
  </item>
  <item UID="3032" plugin="AISprite" name="AISprite3025" cacheAsBitmap="false" parallaxX="100" parallaxY="100" index="7" family="displayobject">
    <item name="name" value="AISprite3025" valueDataType="string"/>
    <item name="uiGuid" value="3032" valueDataType="string"/>
    <item name="global" value="false" valueDataType="boolean"/>
    <item name="visible" value="true" valueDataType="boolean"/>
    <item name="x" value="927.6268040433368" valueDataType="number"/>
    <item name="y" value="624.08" valueDataType="number"/>
    <item name="anchorX" value="0.5125748324789843" valueDataType="number"/>
    <item name="anchorY" value="0.5058371085623534" valueDataType="number"/>
    <item name="width" value="128" valueDataType="number"/>
    <item name="height" value="128" valueDataType="number"/>
    <item name="angle" value="0" valueDataType="number"/>
    <item name="alpha" value="1" valueDataType="number"/>
    <item name="url" value="resource%2FuserAsset%2Fimage%2FgrassMid.png" valueDataType="string"/>
    <item name="enabled" value="false" valueDataType="boolean"/>
    <item name="collision" value="true" valueDataType="boolean"/>
    <item name="collisionData" value="0%2Fn0.00%7C128.00%2C128.00%7C128.00%2C128.00%7C0.00%2C0.00%7C0.00" sourceValue="0%2Fn0.00%7C128.00%2C128.00%7C128.00%2C128.00%7C0.00%2C0.00%7C0.00" valueDataType="string"/>
    <item name="layer" value="2" valueDataType="number"/>
    <item name="behaviors">
      <item type="behavior" behaviorType="SolidBehaivor" name="刚体"/>
    </item>
  </item>
  <item UID="3038" plugin="AIMovieClip" name="雪人" cacheAsBitmap="false" parallaxX="100" parallaxY="100" index="8" family="displayobject">
    <item name="name" value="%E9%9B%AA%E4%BA%BA" valueDataType="string"/>
    <item name="uiGuid" value="3038" valueDataType="string"/>
    <item name="global" value="false" valueDataType="boolean"/>
    <item name="visible" value="true" valueDataType="boolean"/>
    <item name="x" value="1117.578657202164" valueDataType="number"/>
    <item name="y" value="439.16" valueDataType="number"/>
    <item name="anchorX" value="0.5042711710197968" valueDataType="number"/>
    <item name="anchorY" value="0.5053956902648524" valueDataType="number"/>
    <item name="width" value="147" valueDataType="number"/>
    <item name="height" value="256" valueDataType="number"/>
    <item name="angle" value="0" valueDataType="number"/>
    <item name="alpha" value="1" valueDataType="number"/>
    <item name="enabled" value="false" valueDataType="boolean"/>
    <item name="collision" value="false" valueDataType="boolean"/>
    <item name="collisionData" value="0%2Fn0.00%7C256.00%2C147.00%7C256.00%2C147.00%7C0.00%2C0.00%7C0.00" sourceValue="0%2Fn0.00%7C256.00%2C147.00%7C256.00%2C147.00%7C0.00%2C0.00%7C0.00" valueDataType="string"/>
    <item name="actions" value="" valueDataType="string">
      <item name="打颤" loop="0" fps="60" scaleX="1" scaleY="1">
        <item src="resource%2FuserAsset%2Fcom%2Ftt6fju-qy0j452.png"/>
        <item src="resource%2FuserAsset%2Fcom%2Ftt6fju.png"/>
      </item>
      <item name="融化" loop="1" fps="1" scaleX="1" scaleY="1">
        <item src="resource%2FuserAsset%2Fcom%2Ftt6fju-qrxgeu1.png"/>
        <item src="resource%2FuserAsset%2Fcom%2Ftt6fju-qrxgeu2.png"/>
        <item src="resource%2FuserAsset%2Fcom%2Ftt6fju-qrxgeu3.png"/>
      </item>
    </item>
    <item name="layer" value="2" valueDataType="number"/>
    <item name="behaviors">
      <item type="behavior" behaviorType="SinBehavior" name="曲线">
        <item valueDataType="number" value="1" name="active"/>
        <item valueDataType="number" value="0" name="movement"/>
        <item valueDataType="number" value="0" name="wave"/>
        <item valueDataType="number" value="10" name="period"/>
        <item valueDataType="number" value="0" name="periodRandom"/>
        <item valueDataType="number" value="0" name="periodOffset"/>
        <item valueDataType="number" value="0" name="periodOffsetRandom"/>
        <item valueDataType="number" value="20" name="magnitude"/>
        <item valueDataType="number" value="0" name="magnitudeRandom"/>
      </item>
    </item>
  </item>
  <item UID="3048" plugin="AIMovieClip" name="篝火" cacheAsBitmap="false" parallaxX="100" parallaxY="100" index="9" family="displayobject">
    <item name="name" value="%E7%AF%9D%E7%81%AB" valueDataType="string"/>
    <item name="uiGuid" value="3048" valueDataType="string"/>
    <item name="global" value="false" valueDataType="boolean"/>
    <item name="visible" value="true" valueDataType="boolean"/>
    <item name="x" value="781.3926892230045" valueDataType="number"/>
    <item name="y" value="494.2472073238446" valueDataType="number"/>
    <item name="anchorX" value="0.5" valueDataType="number"/>
    <item name="anchorY" value="0.5" valueDataType="number"/>
    <item name="width" value="94" valueDataType="number"/>
    <item name="height" value="131" valueDataType="number"/>
    <item name="angle" value="0" valueDataType="number"/>
    <item name="alpha" value="1" valueDataType="number"/>
    <item name="enabled" value="false" valueDataType="boolean"/>
    <item name="collision" value="true" valueDataType="boolean"/>
    <item name="collisionData" value="0%2Fn94.00%7C131.00%2C86.65%7C101.55%2C85.50%7C109.80_68.65%7C88.35%2C40.80%7C77.90%2C44.50%7C81.50_0.00%7C131.00%2C94.00%7C131.00%2C85.50%7C109.80%2C70.85%7C98.85_70.85%7C98.85%2C72.15%7C97.40%2C68.65%7C88.35%2C44.50%7C81.50%2C-1.35%7C118.00%2C0.00%7C131.00" sourceValue="0%2Fn0.00%7C131.00%2C94.00%7C131.00%2C86.65%7C101.55%2C85.50%7C109.80%2C70.85%7C98.85%2C72.15%7C97.40%2C68.65%7C88.35%2C40.80%7C77.90%2C44.50%7C81.50%2C-1.35%7C118.00" valueDataType="string"/>
    <item name="actions" value="" valueDataType="string">
      <item name="没点燃" loop="0" fps="6" scaleX="1" scaleY="1">
        <item src="resource%2FuserAsset%2Fcom%2Fkdkkeohdy.png"/>
      </item>
      <item name="run" loop="0" fps="6" scaleX="1" scaleY="1">
        <item src="resource%2FuserAsset%2Fcom%2Fkdkkeohdy-m7f1.png"/>
        <item src="resource%2FuserAsset%2Fcom%2Fkdkkeohdy-m7f2.png"/>
      </item>
    </item>
    <item name="layer" value="2" valueDataType="number"/>
  </item>
  <item UID="3051" plugin="AIMovieClip" name="对话框" cacheAsBitmap="false" parallaxX="100" parallaxY="100" index="10" family="displayobject">
    <item name="name" value="%E5%AF%B9%E8%AF%9D%E6%A1%86" valueDataType="string"/>
    <item name="uiGuid" value="3051" valueDataType="string"/>
    <item name="global" value="false" valueDataType="boolean"/>
    <item name="visible" value="true" valueDataType="boolean"/>
    <item name="x" value="1231.0426213517921" valueDataType="number"/>
    <item name="y" value="329.7475155532701" valueDataType="number"/>
    <item name="anchorX" value="0.5" valueDataType="number"/>
    <item name="anchorY" value="0.5" valueDataType="number"/>
    <item name="width" value="164" valueDataType="number"/>
    <item name="height" value="157" valueDataType="number"/>
    <item name="angle" value="0" valueDataType="number"/>
    <item name="alpha" value="1" valueDataType="number"/>
    <item name="enabled" value="false" valueDataType="boolean"/>
    <item name="collision" value="false" valueDataType="boolean"/>
    <item name="collisionData" value="0%2Fn0.00%7C157.00%2C164.00%7C157.00%2C164.00%7C0.00%2C0.00%7C0.00" sourceValue="0%2Fn0.00%7C157.00%2C164.00%7C157.00%2C164.00%7C0.00%2C0.00%7C0.00" valueDataType="string"/>
    <item name="actions" value="" valueDataType="string">
      <item name="run" loop="0" fps="4" scaleX="1" scaleY="1">
        <item src="resource%2FuserAsset%2Fcom%2Frmlkli1.png"/>
        <item src="resource%2FuserAsset%2Fcom%2Frmlkli2.png"/>
      </item>
    </item>
    <item name="layer" value="2" valueDataType="number"/>
    <item name="behaviors">
      <item type="behavior" behaviorType="FadeBehavior" name="淡入淡出">
        <item valueDataType="number" value="0" name="activeAtStartType"/>
        <item valueDataType="number" value="1" name="fadeInTime"/>
        <item valueDataType="number" value="0" name="waitTime"/>
        <item valueDataType="number" value="0" name="fadeOutTime"/>
        <item valueDataType="number" value="1" name="loopTimes"/>
        <item valueDataType="number" value="0" name="destoryType"/>
      </item>
    </item>
  </item>
  <item UID="3054" plugin="AIMovieClip" name="雪人文字" cacheAsBitmap="false" parallaxX="100" parallaxY="100" index="11" family="displayobject">
    <item name="name" value="%E9%9B%AA%E4%BA%BA%E6%96%87%E5%AD%97" valueDataType="string"/>
    <item name="uiGuid" value="3054" valueDataType="string"/>
    <item name="global" value="false" valueDataType="boolean"/>
    <item name="visible" value="true" valueDataType="boolean"/>
    <item name="x" value="1227.2138585351047" valueDataType="number"/>
    <item name="y" value="317.30970025935017" valueDataType="number"/>
    <item name="anchorX" value="0.3611848845725472" valueDataType="number"/>
    <item name="anchorY" value="0.8363113609293508" valueDataType="number"/>
    <item name="width" value="106" valueDataType="number"/>
    <item name="height" value="45" valueDataType="number"/>
    <item name="angle" value="0" valueDataType="number"/>
    <item name="alpha" value="1" valueDataType="number"/>
    <item name="enabled" value="false" valueDataType="boolean"/>
    <item name="collision" value="false" valueDataType="boolean"/>
    <item name="collisionData" value="0%2Fn0.00%7C45.00%2C106.00%7C45.00%2C106.00%7C0.00%2C0.00%7C0.00" sourceValue="0%2Fn0.00%7C45.00%2C106.00%7C45.00%2C106.00%7C0.00%2C0.00%7C0.00" valueDataType="string"/>
    <item name="actions" value="" valueDataType="string">
      <item name="run" loop="2" fps="1" scaleX="1" scaleY="1">
        <item src="resource%2FuserAsset%2Fcom%2Fk1zi1j-s6jfgatt6fjujddiz2fgo.png"/>
        <item src="resource%2FuserAsset%2Fcom%2Fk1zi1j-hodg53gui.png"/>
      </item>
      <item name="warm" loop="0" fps="6" scaleX="1" scaleY="1">
        <item src="resource%2FuserAsset%2Fcom%2Fk1zi1j-ginkf9jddff1rn8tt6fjugui.png"/>
      </item>
    </item>
    <item name="layer" value="2" valueDataType="number"/>
  </item>
  <item UID="3057" plugin="AIMovieClip" name="火箭" cacheAsBitmap="false" parallaxX="100" parallaxY="100" index="12" family="displayobject">
    <item name="name" value="%E7%81%AB%E7%AE%AD" valueDataType="string"/>
    <item name="uiGuid" value="3057" valueDataType="string"/>
    <item name="global" value="false" valueDataType="boolean"/>
    <item name="visible" value="true" valueDataType="boolean"/>
    <item name="x" value="1806.9056841242564" valueDataType="number"/>
    <item name="y" value="111.4141122431882" valueDataType="number"/>
    <item name="anchorX" value="0.5094674036637035" valueDataType="number"/>
    <item name="anchorY" value="0.45281645793482567" valueDataType="number"/>
    <item name="width" value="118" valueDataType="number"/>
    <item name="height" value="228.46004935558497" valueDataType="number"/>
    <item name="angle" value="344.111418376433" valueDataType="number"/>
    <item name="alpha" value="1" valueDataType="number"/>
    <item name="enabled" value="true" valueDataType="boolean"/>
    <item name="collision" value="true" valueDataType="boolean"/>
    <item name="collisionData" value="0%2Fn38.75%7C186.50%2C65.75%7C221.50%2C89.85%7C187.95%2C72.90%7C157.25%2C41.40%7C160.95" sourceValue="0%2Fn38.75%7C186.50%2C65.75%7C221.50%2C89.85%7C187.95%2C72.90%7C157.25%2C41.40%7C160.95" valueDataType="string"/>
    <item name="actions" value="" valueDataType="string">
      <item name="run" loop="0" fps="6" scaleX="1" scaleY="1">
        <item src="resource%2FuserAsset%2Fcom%2Fm7fofh2.png"/>
        <item src="resource%2FuserAsset%2Fcom%2Fm7fofh1.png"/>
      </item>
    </item>
    <item name="layer" value="2" valueDataType="number"/>
    <item name="behaviors">
      <item type="behavior" behaviorType="DragDropBehaivor" name="拖拽">
        <item valueDataType="number" value="0" name="axes"/>
        <item valueDataType="number" value="1" name="enabled"/>
      </item>
      <item type="behavior" behaviorType="SolidBehaivor" name="刚体"/>
      <item type="behavior" behaviorType="DestoryOutsideLayoutBehaivor" name="出界销毁">
        <item valueDataType="number" value="1" name="type"/>
      </item>
    </item>
  </item>
</layout>